[{"status":1,"score":0,"tags":"","is_rewatching":0,"num_watched_episodes":7,"anime_title":"Demi-chan wa Kataritai","anime_title_eng":"Interviews With Monster Girls","anime_num_episodes":12,"anime_airing_status":2,"anime_id":33988,"anime_studios":null,"anime_licensors":null,"anime_season":null,"has_episode_video":false,"has_promotion_video":true,"has_video":true,"video_url":"/anime/33988/Demi-chan_wa_Kataritai/video","genres":[{"id":4,"name":"Comedy"},{"id":10,"name":"Fantasy"}],"demographics":[{"id":42,"name":"Seinen"}],"title_localized":null,"anime_url":"/anime/33988/Demi-chan_wa_Kataritai","anime_image_path":"https://cdn.myanimelist.net/r/96x136/images/anime/8/83417.jpg?s=e751f867a5171d09c47fd9bbc7a6db26","is_added_to_list":false,"anime_media_type_string":"TV","anime_mpaa_rating_string":"PG-13","start_date_string":null,"finish_date_string":null,"anime_start_date_string":"08-01-17","anime_end_date_string":"26-03-17","days_string":null,"storage_string":"","priority_string":"Low"},{"status":1,"score":0,"tags":"","is_rewatching":0,"num_watched_episodes":3,"anime_title":"Gintama","anime_title_eng":"Gintama","anime_num_episodes":201,"anime_airing_status":2,"anime_id":918,"anime_studios":null,"anime_licensors":null,"anime_season":null,"has_episode_video":true,"has_promotion_video":false,"has_video":true,"video_url":"/anime/918/Gintama/video","genres":[{"id":1,"name":"Action"},{"id":4,"name":"Comedy"},{"id":24,"name":"Sci-Fi"}],"demographics":[{"id":27,"name":"Shounen"}],"title_localized":null,"anime_url":"/anime/918/Gintama","anime_image_path":"https://cdn.myanimelist.net/r/96x136/images/anime/10/73274.jpg?s=ebdd0535c426dbf5ba1522d3c5006674","is_added_to_list":false,"anime_media_type_string":"TV","anime_mpaa_rating_string":"PG-13","start_date_string":null,"finish_date_string":null,"anime_start_date_string":"04-04-06","anime_end_date_string":"25-03-10","days_string":null,"storage_string":"","priority_string":"Low"},{"status":1,"score":0,"tags":"","is_rewatching":0,"num_watched_episodes":3,"anime_title":"Horimiya","anime_title_eng":"Horimiya","anime_num_episodes":13,"anime_airing_status":2,"anime_id":42897,"anime_studios":null,"anime_licensors":null,"anime_season":null,"has_episode_video":false,"has_promotion_video":true,"has_video":true,"video_url":"/anime/42897/Horimiya/video","genres":[{"id":4,"name":"Comedy"},{"id":22,"name":"Romance"},{"id":36,"name":"Slice of Life"}],"demographics":[{"id":27,"name":"Shounen"}],"title_localized":null,"anime_url":"/anime/42897/Horimiya","anime_image_path":"https://cdn.myanimelist.net/r/96x136/images/anime/1695/111486.jpg?s=68952f0e26a9e966ec8731f2256a7057","is_added_to_list":false,"anime_media_type_string":"TV","anime_mpaa_rating_string":"PG-13","start_date_string":null,"finish_date_string":null,"anime_start_date_string":"10-01-21","anime_end_date_string":"04-04-21","days_string":null,"storage_string":"","priority_string":"Low"},{"status":1,"score":0,"tags":"","is_rewatching":0,"num_watched_episodes":5,"anime_title":"Mob Psycho 100 II","anime_title_eng":"Mob Psycho 100 II","anime_num_episodes":13,"anime_airing_status":2,"anime_id":37510,"anime_studios":null,"anime_licensors":null,"anime_season":null,"has_episode_video":true,"has_promotion_video":true,"has_video":true,"video_url":"/anime/37510/Mob_Psycho_100_II/video","genres":[{"id":1,"name":"Action"},{"id":4,"name":"Comedy"},{"id":36,"name":"Slice of Life"},{"id":37,"name":"Supernatural"}],"demographics":[],"title_localized":null,"anime_url":"/anime/37510/Mob_Psycho_100_II","anime_image_path":"https://cdn.myanimelist.net/r/96x136/images/anime/1918/96303.jpg?s=08c4432121bf6645278efe8d303f5ee6","is_added_to_list":false,"anime_media_type_string":"TV","anime_mpaa_rating_string":"PG-13","start_date_string":null,"finish_date_string":null,"anime_start_date_string":"07-01-19","anime_end_date_string":"01-04-19","days_string":null,"storage_string":"","priority_string":"Low"},{"status":1,"score":0,"tags":"","is_rewatching":0,"num_watched_episodes":6,"anime_title":"Nanbaka","anime_title_eng":"Nanbaka","anime_num_episodes":13,"anime_airing_status":2,"anime_id":30016,"anime_studios":null,"anime_licensors":null,"anime_season":null,"has_episode_video":true,"has_promotion_video":true,"has_video":true,"video_url":"/anime/30016/Nanbaka/video","genres":[{"id":1,"name":"Action"},{"id":4,"name":"Comedy"},{"id":8,"name":"Drama"}],"demographics":[],"title_localized":null,"anime_url":"/anime/30016/Nanbaka","anime_image_path":"https://cdn.myanimelist.net/r/96x136/images/anime/2/81399.jpg?s=c30a499b3708ccff5ab771584d053903","is_added_to_list":false,"anime_media_type_string":"TV","anime_mpaa_rating_string":"PG-13","start_date_string":null,"finish_date_string":null,"anime_start_date_string":"05-10-16","anime_end_date_string":"28-12-16","days_string":null,"storage_string":"","priority_string":"Low"},{"status":1,"score":0,"tags":"","is_rewatching":0,"num_watched_episodes":2,"anime_title":"One Piece","anime_title_eng":"One Piece","anime_num_episodes":0,"anime_airing_status":1,"anime_id":21,"anime_studios":null,"anime_licensors":null,"anime_season":null,"has_episode_video":true,"has_promotion_video":true,"has_video":true,"video_url":"/anime/21/One_Piece/video","genres":[{"id":1,"name":"Action"},{"id":2,"name":"Adventure"},{"id":4,"name":"Comedy"},{"id":8,"name":"Drama"},{"id":10,"name":"Fantasy"}],"demographics":[{"id":27,"name":"Shounen"}],"title_localized":null,"anime_url":"/anime/21/One_Piece","anime_image_path":"https://cdn.myanimelist.net/r/96x136/images/anime/6/73245.jpg?s=539a3133deab14f1741620a19dd10e7f","is_added_to_list":false,"anime_media_type_string":"TV","anime_mpaa_rating_string":"PG-13","start_date_string":null,"finish_date_string":null,"anime_start_date_string":"20-10-99","anime_end_date_string":null,"days_string":null,"storage_string":"","priority_string":"Low"},{"status":1,"score":10,"tags":"","is_rewatching":0,"num_watched_episodes":5,"anime_title":"Sakurako-san no Ashimoto ni wa Shitai ga Umatteiru","anime_title_eng":"Beautiful Bones -Sakurako's Investigation-","anime_num_episodes":12,"anime_airing_status":2,"anime_id":30187,"anime_studios":null,"anime_licensors":null,"anime_season":null,"has_episode_video":false,"has_promotion_video":true,"has_video":true,"video_url":"/anime/30187/Sakurako-san_no_Ashimoto_ni_wa_Shitai_ga_Umatteiru/video","genres":[{"id":8,"name":"Drama"},{"id":7,"name":"Mystery"},{"id":41,"name":"Suspense"}],"demographics":[],"title_localized":null,"anime_url":"/anime/30187/Sakurako-san_no_Ashimoto_ni_wa_Shitai_ga_Umatteiru","anime_image_path":"https://cdn.myanimelist.net/r/96x136/images/anime/7/76116.jpg?s=27eb32b34782eaa2a3470750988d3847","is_added_to_list":false,"anime_media_type_string":"TV","anime_mpaa_rating_string":"R","start_date_string":"22-06-21","finish_date_string":null,"anime_start_date_string":"08-10-15","anime_end_date_string":"24-12-15","days_string":240,"storage_string":"","priority_string":"Low"},{"status":1,"score":0,"tags":"","is_rewatching":0,"num_watched_episodes":2,"anime_title":"Sword Art Online","anime_title_eng":"Sword Art Online","anime_num_episodes":25,"anime_airing_status":2,"anime_id":11757,"anime_studios":null,"anime_licensors":null,"anime_season":null,"has_episode_video":true,"has_promotion_video":true,"has_video":true,"video_url":"/anime/11757/Sword_Art_Online/video","genres":[{"id":1,"name":"Action"},{"id":2,"name":"Adventure"},{"id":10,"name":"Fantasy"},{"id":22,"name":"Romance"}],"demographics":[],"title_localized":null,"anime_url":"/anime/11757/Sword_Art_Online","anime_image_path":"https://cdn.myanimelist.net/r/96x136/images/anime/11/39717.jpg?s=05cc3cdfc451395e2c3b3dcfb46c5d7d","is_added_to_list":false,"anime_media_type_string":"TV","anime_mpaa_rating_string":"PG-13","start_date_string":"11-05-21","finish_date_string":null,"anime_start_date_string":"08-07-12","anime_end_date_string":"23-12-12","days_string":282,"storage_string":"","priority_string":"Low"},{"status":2,"score":0,"tags":"","is_rewatching":0,"num_watched_episodes":1,"anime_title":"Biohazard: Damnation","anime_title_eng":"","anime_num_episodes":1,"anime_airing_status":2,"anime_id":9544,"anime_studios":null,"anime_licensors":null,"anime_season":null,"has_episode_video":false,"has_promotion_video":false,"has_video":false,"video_url":"/anime/9544/Biohazard__Damnation/video","genres":[{"id":1,"name":"Action"},{"id":14,"name":"Horror"},{"id":24,"name":"Sci-Fi"}],"demographics":[],"title_localized":null,"anime_url":"/anime/9544/Biohazard__Damnation","anime_image_path":"https://cdn.myanimelist.net/r/96x136/images/anime/1224/98799.jpg?s=c45cc66c6394846004daab54ee531698","is_added_to_list":false,"anime_media_type_string":"Movie","anime_mpaa_rating_string":"R","start_date_string":null,"finish_date_string":"02-10-21","anime_start_date_string":"15-09-12","anime_end_date_string":"15-09-12","days_string":null,"storage_string":"","priority_string":"Low"},{"status":2,"score":0,"tags":"","is_rewatching":0,"num_watched_episodes":1,"anime_title":"Biohazard: Degeneration","anime_title_eng":"","anime_num_episodes":1,"anime_airing_status":2,"anime_id":3446,"anime_studios":null,"anime_licensors":null,"anime_season":null,"has_episode_video":false,"has_promotion_video":false,"has_video":false,"video_url":"/anime/3446/Biohazard__Degeneration/video","genres":[{"id":1,"name":"Action"},{"id":14,"name":"Horror"},{"id":24,"name":"Sci-Fi"}],"demographics":[],"title_localized":null,"anime_url":"/anime/3446/Biohazard__Degeneration","anime_image_path":"https://cdn.myanimelist.net/r/96x136/images/anime/4/11769.jpg?s=73d6285a9abc9cdcb1713789ca32ad7e","is_added_to_list":false,"anime_media_type_string":"Movie","anime_mpaa_rating_string":"R","start_date_string":null,"finish_date_string":"02-10-21","anime_start_date_string":"18-10-08","anime_end_date_string":"18-10-08","days_string":null,"storage_string":"","priority_string":"Low"},{"status":2,"score":10,"tags":"","is_rewatching":0,"num_watched_episodes":4,"anime_title":"Biohazard: Infinite Darkness","anime_title_eng":"","anime_num_episodes":4,"anime_airing_status":2,"anime_id":42976,"anime_studios":null,"anime_licensors":null,"anime_season":null,"has_episode_video":false,"has_promotion_video":true,"has_video":true,"video_url":"/anime/42976/Biohazard__Infinite_Darkness/video","genres":[{"id":1,"name":"Action"},{"id":14,"name":"Horror"},{"id":24,"name":"Sci-Fi"}],"demographics":[],"title_localized":null,"anime_url":"/anime/42976/Biohazard__Infinite_Darkness","anime_image_path":"https://cdn.myanimelist.net/r/96x136/images/anime/1261/119378.jpg?s=8c0100bf4dba684df2e6f2c6be8baca1","is_added_to_list":false,"anime_media_type_string":"ONA","anime_mpaa_rating_string":"R","start_date_string":"02-10-21","finish_date_string":"02-10-21","anime_start_date_string":"08-07-21","anime_end_date_string":"08-07-21","days_string":1,"storage_string":"","priority_string":"Low"},{"status":2,"score":0,"tags":"","is_rewatching":0,"num_watched_episodes":1,"anime_title":"Biohazard: Vendetta","anime_title_eng":"Resident Evil: Vendetta","anime_num_episodes":1,"anime_airing_status":2,"anime_id":31853,"anime_studios":null,"anime_licensors":null,"anime_season":null,"has_episode_video":false,"has_promotion_video":true,"has_video":true,"video_url":"/anime/31853/Biohazard__Vendetta/video","genres":[{"id":1,"name":"Action"},{"id":14,"name":"Horror"},{"id":24,"name":"Sci-Fi"}],"demographics":[],"title_localized":null,"anime_url":"/anime/31853/Biohazard__Vendetta","anime_image_path":"https://cdn.myanimelist.net/r/96x136/images/anime/6/83300.jpg?s=63806fc1d51e502dacc4c44487798108","is_added_to_list":false,"anime_media_type_string":"Movie","anime_mpaa_rating_string":"R","start_date_string":"02-10-21","finish_date_string":"02-10-21","anime_start_date_string":"27-05-17","anime_end_date_string":"27-05-17","days_string":1,"storage_string":"","priority_string":"Low"},{"status":2,"score":0,"tags":"","is_rewatching":0,"num_watched_episodes":11,"anime_title":"Fugou Keiji: Balance:Unlimited","anime_title_eng":"The Millionaire Detective – Balance: UNLIMITED","anime_num_episodes":11,"anime_airing_status":2,"anime_id":41120,"anime_studios":null,"anime_licensors":null,"anime_season":null,"has_episode_video":false,"has_promotion_video":true,"has_video":true,"video_url":"/anime/41120/Fugou_Keiji__Balance_Unlimited/video","genres":[{"id":4,"name":"Comedy"},{"id":7,"name":"Mystery"}],"demographics":[],"title_localized":null,"anime_url":"/anime/41120/Fugou_Keiji__Balance_Unlimited","anime_image_path":"https://cdn.myanimelist.net/r/96x136/images/anime/1066/106556.jpg?s=5f284cf7a0d1805a49e425b5e0d1dcf8","is_added_to_list":false,"anime_media_type_string":"TV","anime_mpaa_rating_string":"PG-13","start_date_string":null,"finish_date_string":"15-01-22","anime_start_date_string":"10-04-20","anime_end_date_string":"25-09-20","days_string":null,"storage_string":"","priority_string":"Low"},{"status":2,"score":9,"tags":"","is_rewatching":0,"num_watched_episodes":1,"anime_title":"Gantz:O","anime_title_eng":"","anime_num_episodes":1,"anime_airing_status":2,"anime_id":32071,"anime_studios":null,"anime_licensors":null,"anime_season":null,"has_episode_video":false,"has_promotion_video":true,"has_video":true,"video_url":"/anime/32071/Gantz_O/video","genres":[{"id":1,"name":"Action"},{"id":8,"name":"Drama"},{"id":14,"name":"Horror"},{"id":24,"name":"Sci-Fi"},{"id":37,"name":"Supernatural"},{"id":9,"name":"Ecchi"}],"demographics":[{"id":42,"name":"Seinen"}],"title_localized":null,"anime_url":"/anime/32071/Gantz_O","anime_image_path":"https://cdn.myanimelist.net/r/96x136/images/anime/7/81255.jpg?s=f125b31a9e84b13b88b862be1d1a4add","is_added_to_list":false,"anime_media_type_string":"Movie","anime_mpaa_rating_string":"R+","start_date_string":null,"finish_date_string":null,"anime_start_date_string":"14-10-16","anime_end_date_string":"14-10-16","days_string":null,"storage_string":"","priority_string":"Low"},{"status":2,"score":0,"tags":"","is_rewatching":0,"num_watched_episodes":5,"anime_title":"Gokushufudou","anime_title_eng":"The Way of the Househusband","anime_num_episodes":5,"anime_airing_status":2,"anime_id":43692,"anime_studios":null,"anime_licensors":null,"anime_season":null,"has_episode_video":false,"has_promotion_video":true,"has_video":true,"video_url":"/anime/43692/Gokushufudou/video","genres":[{"id":4,"name":"Comedy"},{"id":22,"name":"Romance"},{"id":36,"name":"Slice of Life"}],"demographics":[],"title_localized":null,"anime_url":"/anime/43692/Gokushufudou","anime_image_path":"https://cdn.myanimelist.net/r/96x136/images/anime/1535/117726.jpg?s=b917eb6485894f031da115ad4df82ad1","is_added_to_list":false,"anime_media_type_string":"ONA","anime_mpaa_rating_string":"PG-13","start_date_string":null,"finish_date_string":null,"anime_start_date_string":"08-04-21","anime_end_date_string":"08-04-21","days_string":null,"storage_string":"","priority_string":"Low"},{"status":2,"score":0,"tags":"","is_rewatching":0,"num_watched_episodes":5,"anime_title":"Gokushufudou Part 2","anime_title_eng":"","anime_num_episodes":5,"anime_airing_status":2,"anime_id":48707,"anime_studios":null,"anime_licensors":null,"anime_season":null,"has_episode_video":false,"has_promotion_video":true,"has_video":true,"video_url":"/anime/48707/Gokushufudou_Part_2/video","genres":[{"id":4,"name":"Comedy"},{"id":22,"name":"Romance"},{"id":36,"name":"Slice of Life"}],"demographics":[],"title_localized":null,"anime_url":"/anime/48707/Gokushufudou_Part_2","anime_image_path":"https://cdn.myanimelist.net/r/96x136/images/anime/1942/120785.jpg?s=6dc37e843e3d410db9f7c55dc50092a2","is_added_to_list":false,"anime_media_type_string":"ONA","anime_mpaa_rating_string":"PG-13","start_date_string":null,"finish_date_string":null,"anime_start_date_string":"07-10-21","anime_end_date_string":"07-10-21","days_string":null,"storage_string":"","priority_string":"Low"},{"status":2,"score":0,"tags":"","is_rewatching":0,"num_watched_episodes":12,"anime_title":"High School DxD","anime_title_eng":"High School DxD","anime_num_episodes":12,"anime_airing_status":2,"anime_id":11617,"anime_studios":null,"anime_licensors":null,"anime_season":null,"has_episode_video":false,"has_promotion_video":true,"has_video":true,"video_url":"/anime/11617/High_School_DxD/video","genres":[{"id":4,"name":"Comedy"},{"id":22,"name":"Romance"},{"id":9,"name":"Ecchi"}],"demographics":[],"title_localized":null,"anime_url":"/anime/11617/High_School_DxD","anime_image_path":"https://cdn.myanimelist.net/r/96x136/images/anime/1331/111940.jpg?s=a08e921cc15492e80504aeb4f0f8ab9c","is_added_to_list":false,"anime_media_type_string":"TV","anime_mpaa_rating_string":"R+","start_date_string":null,"finish_date_string":null,"anime_start_date_string":"06-01-12","anime_end_date_string":"23-03-12","days_string":null,"storage_string":"","priority_string":"Low"},{"status":2,"score":9,"tags":"","is_rewatching":0,"num_watched_episodes":12,"anime_title":"Highschool of the Dead","anime_title_eng":"High School of the Dead","anime_num_episodes":12,"anime_airing_status":2,"anime_id":8074,"anime_studios":null,"anime_licensors":null,"anime_season":null,"has_episode_video":false,"has_promotion_video":true,"has_video":true,"video_url":"/anime/8074/Highschool_of_the_Dead/video","genres":[{"id":1,"name":"Action"},{"id":14,"name":"Horror"},{"id":37,"name":"Supernatural"},{"id":9,"name":"Ecchi"}],"demographics":[{"id":27,"name":"Shounen"}],"title_localized":null,"anime_url":"/anime/8074/Highschool_of_the_Dead","anime_image_path":"https://cdn.myanimelist.net/r/96x136/images/anime/11/78311.jpg?s=07d98a4714ff7541edf320ff93f903fe","is_added_to_list":false,"anime_media_type_string":"TV","anime_mpaa_rating_string":"R+","start_date_string":null,"finish_date_string":null,"anime_start_date_string":"05-07-10","anime_end_date_string":"20-09-10","days_string":null,"storage_string":"","priority_string":"Low"},{"status":2,"score":0,"tags":"","is_rewatching":0,"num_watched_episodes":1,"anime_title":"Highschool of the Dead: Drifters of the Dead","anime_title_eng":"","anime_num_episodes":1,"anime_airing_status":2,"anime_id":9515,"anime_studios":null,"anime_licensors":null,"anime_season":null,"has_episode_video":false,"has_promotion_video":false,"has_video":false,"video_url":"/anime/9515/Highschool_of_the_Dead__Drifters_of_the_Dead/video","genres":[{"id":4,"name":"Comedy"},{"id":37,"name":"Supernatural"},{"id":9,"name":"Ecchi"}],"demographics":[],"title_localized":null,"anime_url":"/anime/9515/Highschool_of_the_Dead__Drifters_of_the_Dead","anime_image_path":"https://cdn.myanimelist.net/r/96x136/images/anime/1746/97780.jpg?s=73bc74fc21b24ab96398a6ebe45c99ff","is_added_to_list":false,"anime_media_type_string":"OVA","anime_mpaa_rating_string":"R+","start_date_string":null,"finish_date_string":null,"anime_start_date_string":"26-04-11","anime_end_date_string":"26-04-11","days_string":null,"storage_string":"","priority_string":"Low"},{"status":2,"score":8,"tags":"","is_rewatching":0,"num_watched_episodes":12,"anime_title":"Hundred","anime_title_eng":"Hundred","anime_num_episodes":12,"anime_airing_status":2,"anime_id":31338,"anime_studios":null,"anime_licensors":null,"anime_season":null,"has_episode_video":true,"has_promotion_video":true,"has_video":true,"video_url":"/anime/31338/Hundred/video","genres":[{"id":1,"name":"Action"},{"id":22,"name":"Romance"},{"id":24,"name":"Sci-Fi"},{"id":9,"name":"Ecchi"}],"demographics":[],"title_localized":null,"anime_url":"/anime/31338/Hundred","anime_image_path":"https://cdn.myanimelist.net/r/96x136/images/anime/3/78858.jpg?s=1f14747b56f21c426043379f54ebab51","is_added_to_list":false,"anime_media_type_string":"TV","anime_mpaa_rating_string":"PG-13","start_date_string":null,"finish_date_string":null,"anime_start_date_string":"05-04-16","anime_end_date_string":"21-06-16","days_string":null,"storage_string":"","priority_string":"Low"},{"status":2,"score":0,"tags":"","is_rewatching":0,"num_watched_episodes":12,"anime_title":"Isekai wa Smartphone to Tomo ni.","anime_title_eng":"In Another World With My Smartphone","anime_num_episodes":12,"anime_airing_status":2,"anime_id":35203,"anime_studios":null,"anime_licensors":null,"anime_season":null,"has_episode_video":true,"has_promotion_video":true,"has_video":true,"video_url":"/anime/35203/Isekai_wa_Smartphone_to_Tomo_ni/video","genres":[{"id":2,"name":"Adventure"},{"id":4,"name":"Comedy"},{"id":10,"name":"Fantasy"},{"id":22,"name":"Romance"}],"demographics":[],"title_localized":null,"anime_url":"/anime/35203/Isekai_wa_Smartphone_to_Tomo_ni","anime_image_path":"https://cdn.myanimelist.net/r/96x136/images/anime/7/86794.jpg?s=f492fee9c6b5e95628da427ff91b92dd","is_added_to_list":false,"anime_media_type_string":"TV","anime_mpaa_rating_string":"PG-13","start_date_string":null,"finish_date_string":null,"anime_start_date_string":"11-07-17","anime_end_date_string":"26-09-17","days_string":null,"storage_string":"","priority_string":"Low"},{"status":2,"score":8,"tags":"","is_rewatching":0,"num_watched_episodes":12,"anime_title":"Kawaikereba Hentai demo Suki ni Natte Kuremasu ka?","anime_title_eng":"Hensuki: Are you willing to fall in love with a pervert, as long as she's a cutie?","anime_num_episodes":12,"anime_airing_status":2,"anime_id":39326,"anime_studios":null,"anime_licensors":null,"anime_season":null,"has_episode_video":false,"has_promotion_video":true,"has_video":true,"video_url":"/anime/39326/Kawaikereba_Hentai_demo_Suki_ni_Natte_Kuremasu_ka/video","genres":[{"id":4,"name":"Comedy"},{"id":22,"name":"Romance"},{"id":9,"name":"Ecchi"}],"demographics":[],"title_localized":null,"anime_url":"/anime/39326/Kawaikereba_Hentai_demo_Suki_ni_Natte_Kuremasu_ka","anime_image_path":"https://cdn.myanimelist.net/r/96x136/images/anime/1430/102439.jpg?s=e47d0634bfdec7c881a1c62dfbddbf66","is_added_to_list":false,"anime_media_type_string":"TV","anime_mpaa_rating_string":"PG-13","start_date_string":null,"finish_date_string":null,"anime_start_date_string":"08-07-19","anime_end_date_string":"23-09-19","days_string":null,"storage_string":"","priority_string":"Low"},{"status":2,"score":5,"tags":"","is_rewatching":0,"num_watched_episodes":1,"anime_title":"Kimi wa Kanata","anime_title_eng":"Over the Sky","anime_num_episodes":1,"anime_airing_status":2,"anime_id":41379,"anime_studios":null,"anime_licensors":null,"anime_season":null,"has_episode_video":false,"has_promotion_video":true,"has_video":true,"video_url":"/anime/41379/Kimi_wa_Kanata/video","genres":[{"id":8,"name":"Drama"},{"id":10,"name":"Fantasy"}],"demographics":[],"title_localized":null,"anime_url":"/anime/41379/Kimi_wa_Kanata","anime_image_path":"https://cdn.myanimelist.net/r/96x136/images/anime/1724/109743.jpg?s=91e1075fb958d4d415c19ee7e5a59cb6","is_added_to_list":false,"anime_media_type_string":"Movie","anime_mpaa_rating_string":null,"start_date_string":null,"finish_date_string":null,"anime_start_date_string":"27-11-20","anime_end_date_string":"27-11-20","days_string":null,"storage_string":"","priority_string":"Low"},{"status":2,"score":0,"tags":"","is_rewatching":0,"num_watched_episodes":12,"anime_title":"Komi-san wa, Comyushou desu.","anime_title_eng":"Komi Can't Communicate","anime_num_episodes":12,"anime_airing_status":2,"anime_id":48926,"anime_studios":null,"anime_licensors":null,"anime_season":null,"has_episode_video":false,"has_promotion_video":true,"has_video":true,"video_url":"/anime/48926/Komi-san_wa_Comyushou_desu/video","genres":[{"id":4,"name":"Comedy"},{"id":36,"name":"Slice of Life"}],"demographics":[{"id":27,"name":"Shounen"}],"title_localized":null,"anime_url":"/anime/48926/Komi-san_wa_Comyushou_desu","anime_image_path":"https://cdn.myanimelist.net/r/96x136/images/anime/1899/117237.jpg?s=ca27f42d3561dcd93db479c965037bf1","is_added_to_list":false,"anime_media_type_string":"TV","anime_mpaa_rating_string":"PG-13","start_date_string":null,"finish_date_string":"14-01-22","anime_start_date_string":"07-10-21","anime_end_date_string":"23-12-21","days_string":null,"storage_string":"","priority_string":"Low"},{"status":2,"score":0,"tags":"","is_rewatching":0,"num_watched_episodes":12,"anime_title":"Kore wa Zombie Desu ka?","anime_title_eng":"Is This a Zombie?","anime_num_episodes":12,"anime_airing_status":2,"anime_id":8841,"anime_studios":null,"anime_licensors":null,"anime_season":null,"has_episode_video":false,"has_promotion_video":false,"has_video":false,"video_url":"/anime/8841/Kore_wa_Zombie_Desu_ka/video","genres":[{"id":1,"name":"Action"},{"id":4,"name":"Comedy"},{"id":37,"name":"Supernatural"},{"id":9,"name":"Ecchi"}],"demographics":[],"title_localized":null,"anime_url":"/anime/8841/Kore_wa_Zombie_Desu_ka","anime_image_path":"https://cdn.myanimelist.net/r/96x136/images/anime/13/75521.jpg?s=a1ec9097dea095446bf5d8500e56782c","is_added_to_list":false,"anime_media_type_string":"TV","anime_mpaa_rating_string":"R","start_date_string":null,"finish_date_string":null,"anime_start_date_string":"11-01-11","anime_end_date_string":"30-03-11","days_string":null,"storage_string":"","priority_string":"Low"},{"status":2,"score":0,"tags":"","is_rewatching":0,"num_watched_episodes":23,"anime_title":"Mairimashita! Iruma-kun","anime_title_eng":"Welcome to Demon School! Iruma-kun","anime_num_episodes":23,"anime_airing_status":2,"anime_id":39196,"anime_studios":null,"anime_licensors":null,"anime_season":null,"has_episode_video":true,"has_promotion_video":true,"has_video":true,"video_url":"/anime/39196/Mairimashita_Iruma-kun/video","genres":[{"id":4,"name":"Comedy"},{"id":10,"name":"Fantasy"},{"id":37,"name":"Supernatural"}],"demographics":[{"id":27,"name":"Shounen"}],"title_localized":null,"anime_url":"/anime/39196/Mairimashita_Iruma-kun","anime_image_path":"https://cdn.myanimelist.net/r/96x136/images/anime/1009/103187.jpg?s=333f9a5de78f6314e25a0e629d4acedf","is_added_to_list":false,"anime_media_type_string":"TV","anime_mpaa_rating_string":"PG-13","start_date_string":null,"finish_date_string":"16-02-21","anime_start_date_string":"05-10-19","anime_end_date_string":"07-03-20","days_string":null,"storage_string":"","priority_string":"Low"},{"status":2,"score":0,"tags":"","is_rewatching":0,"num_watched_episodes":12,"anime_title":"Mob Psycho 100","anime_title_eng":"Mob Psycho 100","anime_num_episodes":12,"anime_airing_status":2,"anime_id":32182,"anime_studios":null,"anime_licensors":null,"anime_season":null,"has_episode_video":true,"has_promotion_video":true,"has_video":true,"video_url":"/anime/32182/Mob_Psycho_100/video","genres":[{"id":1,"name":"Action"},{"id":4,"name":"Comedy"},{"id":36,"name":"Slice of Life"},{"id":37,"name":"Supernatural"}],"demographics":[],"title_localized":null,"anime_url":"/anime/32182/Mob_Psycho_100","anime_image_path":"https://cdn.myanimelist.net/r/96x136/images/anime/8/80356.jpg?s=b8271cc89b30e6285a180f8a0a7fb5e7","is_added_to_list":false,"anime_media_type_string":"TV","anime_mpaa_rating_string":"PG-13","start_date_string":null,"finish_date_string":null,"anime_start_date_string":"11-07-16","anime_end_date_string":"27-09-16","days_string":null,"storage_string":"","priority_string":"Low"},{"status":2,"score":0,"tags":"","is_rewatching":0,"num_watched_episodes":1,"anime_title":"Nozoki Ana","anime_title_eng":"","anime_num_episodes":1,"anime_airing_status":2,"anime_id":17157,"anime_studios":null,"anime_licensors":null,"anime_season":null,"has_episode_video":false,"has_promotion_video":false,"has_video":false,"video_url":"/anime/17157/Nozoki_Ana/video","genres":[{"id":4,"name":"Comedy"},{"id":8,"name":"Drama"},{"id":9,"name":"Ecchi"}],"demographics":[],"title_localized":null,"anime_url":"/anime/17157/Nozoki_Ana","anime_image_path":"https://cdn.myanimelist.net/r/96x136/images/anime/1393/116601.jpg?s=17eed1d5f36706a401eb8fead639aa58","is_added_to_list":false,"anime_media_type_string":"OVA","anime_mpaa_rating_string":"R+","start_date_string":null,"finish_date_string":null,"anime_start_date_string":"28-02-13","anime_end_date_string":"28-02-13","days_string":null,"storage_string":"","priority_string":"Low"},{"status":2,"score":0,"tags":"","is_rewatching":0,"num_watched_episodes":12,"anime_title":"One Punch Man","anime_title_eng":"One Punch Man","anime_num_episodes":12,"anime_airing_status":2,"anime_id":30276,"anime_studios":null,"anime_licensors":null,"anime_season":null,"has_episode_video":true,"has_promotion_video":true,"has_video":true,"video_url":"/anime/30276/One_Punch_Man/video","genres":[{"id":1,"name":"Action"},{"id":4,"name":"Comedy"},{"id":24,"name":"Sci-Fi"},{"id":37,"name":"Supernatural"}],"demographics":[],"title_localized":null,"anime_url":"/anime/30276/One_Punch_Man","anime_image_path":"https://cdn.myanimelist.net/r/96x136/images/anime/12/76049.jpg?s=0d01cfdaaef16dd1136e1f9081a3af00","is_added_to_list":false,"anime_media_type_string":"TV","anime_mpaa_rating_string":"R","start_date_string":null,"finish_date_string":null,"anime_start_date_string":"05-10-15","anime_end_date_string":"21-12-15","days_string":null,"storage_string":"","priority_string":"Low"},{"status":2,"score":0,"tags":"","is_rewatching":0,"num_watched_episodes":12,"anime_title":"One Punch Man 2nd Season","anime_title_eng":"One-Punch Man 2","anime_num_episodes":12,"anime_airing_status":2,"anime_id":34134,"anime_studios":null,"anime_licensors":null,"anime_season":null,"has_episode_video":true,"has_promotion_video":true,"has_video":true,"video_url":"/anime/34134/One_Punch_Man_2nd_Season/video","genres":[{"id":1,"name":"Action"},{"id":4,"name":"Comedy"},{"id":24,"name":"Sci-Fi"},{"id":37,"name":"Supernatural"}],"demographics":[],"title_localized":null,"anime_url":"/anime/34134/One_Punch_Man_2nd_Season","anime_image_path":"https://cdn.myanimelist.net/r/96x136/images/anime/1805/99571.jpg?s=76893d6eb26f8add6731bcfa56f243ec","is_added_to_list":false,"anime_media_type_string":"TV","anime_mpaa_rating_string":"R","start_date_string":null,"finish_date_string":null,"anime_start_date_string":"10-04-19","anime_end_date_string":"03-07-19","days_string":null,"storage_string":"","priority_string":"Low"},{"status":2,"score":0,"tags":"","is_rewatching":0,"num_watched_episodes":120,"anime_title":"Saiki Kusuo no Ψ-nan","anime_title_eng":"The Disastrous Life of Saiki K.","anime_num_episodes":120,"anime_airing_status":2,"anime_id":33255,"anime_studios":null,"anime_licensors":null,"anime_season":null,"has_episode_video":false,"has_promotion_video":true,"has_video":true,"video_url":"/anime/33255/Saiki_Kusuo_no_%CE%A8-nan/video","genres":[{"id":4,"name":"Comedy"},{"id":36,"name":"Slice of Life"},{"id":37,"name":"Supernatural"}],"demographics":[{"id":27,"name":"Shounen"}],"title_localized":null,"anime_url":"/anime/33255/Saiki_Kusuo_no_Ψ-nan","anime_image_path":"https://cdn.myanimelist.net/r/96x136/images/anime/11/80167.jpg?s=1f8010b138c8cbed0a1a09124f35ac8d","is_added_to_list":false,"anime_media_type_string":"TV","anime_mpaa_rating_string":"PG-13","start_date_string":null,"finish_date_string":"14-01-22","anime_start_date_string":"04-07-16","anime_end_date_string":"26-12-16","days_string":null,"storage_string":"","priority_string":"Low"},{"status":2,"score":0,"tags":"","is_rewatching":0,"num_watched_episodes":24,"anime_title":"Saiki Kusuo no Ψ-nan 2","anime_title_eng":"The Disastrous Life of Saiki K. 2","anime_num_episodes":24,"anime_airing_status":2,"anime_id":34612,"anime_studios":null,"anime_licensors":null,"anime_season":null,"has_episode_video":false,"has_promotion_video":true,"has_video":true,"video_url":"/anime/34612/Saiki_Kusuo_no_%CE%A8-nan_2/video","genres":[{"id":4,"name":"Comedy"},{"id":36,"name":"Slice of Life"},{"id":37,"name":"Supernatural"}],"demographics":[{"id":27,"name":"Shounen"}],"title_localized":null,"anime_url":"/anime/34612/Saiki_Kusuo_no_Ψ-nan_2","anime_image_path":"https://cdn.myanimelist.net/r/96x136/images/anime/1961/91383.jpg?s=8d388c3e3cabd8c071793e6105bac7a2","is_added_to_list":false,"anime_media_type_string":"TV","anime_mpaa_rating_string":"PG-13","start_date_string":null,"finish_date_string":"14-01-22","anime_start_date_string":"17-01-18","anime_end_date_string":"27-06-18","days_string":null,"storage_string":"","priority_string":"Low"},{"status":2,"score":0,"tags":"","is_rewatching":0,"num_watched_episodes":6,"anime_title":"Saiki Kusuo no Ψ-nan: Ψ-shidou-hen","anime_title_eng":"The Disastrous Life of Saiki K.: Reawakened","anime_num_episodes":6,"anime_airing_status":2,"anime_id":40542,"anime_studios":null,"anime_licensors":null,"anime_season":null,"has_episode_video":false,"has_promotion_video":true,"has_video":true,"video_url":"/anime/40542/Saiki_Kusuo_no_%CE%A8-nan__%CE%A8-shidou-hen/video","genres":[{"id":4,"name":"Comedy"},{"id":36,"name":"Slice of Life"},{"id":37,"name":"Supernatural"}],"demographics":[{"id":27,"name":"Shounen"}],"title_localized":null,"anime_url":"/anime/40542/Saiki_Kusuo_no_Ψ-nan__Ψ-shidou-hen","anime_image_path":"https://cdn.myanimelist.net/r/96x136/images/anime/1993/119022.jpg?s=95bf6a362267d1c6de7390f6197ad510","is_added_to_list":false,"anime_media_type_string":"ONA","anime_mpaa_rating_string":"PG-13","start_date_string":null,"finish_date_string":"15-01-22","anime_start_date_string":"30-12-19","anime_end_date_string":"30-12-19","days_string":null,"storage_string":"","priority_string":"Low"},{"status":2,"score":0,"tags":"","is_rewatching":0,"num_watched_episodes":1,"anime_title":"Saiki Kusuo no Ψ-nan: Kanketsu-hen","anime_title_eng":"The Disastrous Life of Saiki K. Final Arc","anime_num_episodes":1,"anime_airing_status":2,"anime_id":38249,"anime_studios":null,"anime_licensors":null,"anime_season":null,"has_episode_video":false,"has_promotion_video":false,"has_video":false,"video_url":"/anime/38249/Saiki_Kusuo_no_%CE%A8-nan__Kanketsu-hen/video","genres":[{"id":4,"name":"Comedy"},{"id":36,"name":"Slice of Life"},{"id":37,"name":"Supernatural"}],"demographics":[{"id":27,"name":"Shounen"}],"title_localized":null,"anime_url":"/anime/38249/Saiki_Kusuo_no_Ψ-nan__Kanketsu-hen","anime_image_path":"https://cdn.myanimelist.net/r/96x136/images/anime/1159/95661.jpg?s=c22c593d25cdc2fd61b91167ead3130f","is_added_to_list":false,"anime_media_type_string":"Special","anime_mpaa_rating_string":"PG-13","start_date_string":null,"finish_date_string":"14-01-22","anime_start_date_string":"28-12-18","anime_end_date_string":"28-12-18","days_string":null,"storage_string":"","priority_string":"Low"},{"status":2,"score":0,"tags":"","is_rewatching":0,"num_watched_episodes":12,"anime_title":"Sankarea","anime_title_eng":"Sankarea: Undying Love","anime_num_episodes":12,"anime_airing_status":2,"anime_id":11499,"anime_studios":null,"anime_licensors":null,"anime_season":null,"has_episode_video":false,"has_promotion_video":true,"has_video":true,"video_url":"/anime/11499/Sankarea/video","genres":[{"id":4,"name":"Comedy"},{"id":14,"name":"Horror"},{"id":22,"name":"Romance"},{"id":37,"name":"Supernatural"},{"id":9,"name":"Ecchi"}],"demographics":[{"id":27,"name":"Shounen"}],"title_localized":null,"anime_url":"/anime/11499/Sankarea","anime_image_path":"https://cdn.myanimelist.net/r/96x136/images/anime/1487/95651.jpg?s=5493feec380fc248f9acbcaab3dfbdd6","is_added_to_list":false,"anime_media_type_string":"TV","anime_mpaa_rating_string":"R+","start_date_string":null,"finish_date_string":null,"anime_start_date_string":"06-04-12","anime_end_date_string":"29-06-12","days_string":null,"storage_string":"","priority_string":"Low"},{"status":2,"score":0,"tags":"","is_rewatching":0,"num_watched_episodes":12,"anime_title":"Shinchou Yuusha: Kono Yuusha ga Ore Tueee Kuse ni Shinchou Sugiru","anime_title_eng":"Cautious Hero: The Hero Is Overpowered but Overly Cautious","anime_num_episodes":12,"anime_airing_status":2,"anime_id":38659,"anime_studios":null,"anime_licensors":null,"anime_season":null,"has_episode_video":false,"has_promotion_video":true,"has_video":true,"video_url":"/anime/38659/Shinchou_Yuusha__Kono_Yuusha_ga_Ore_Tueee_Kuse_ni_Shinchou_Sugiru/video","genres":[{"id":1,"name":"Action"},{"id":2,"name":"Adventure"},{"id":4,"name":"Comedy"},{"id":10,"name":"Fantasy"}],"demographics":[],"title_localized":null,"anime_url":"/anime/38659/Shinchou_Yuusha__Kono_Yuusha_ga_Ore_Tueee_Kuse_ni_Shinchou_Sugiru","anime_image_path":"https://cdn.myanimelist.net/r/96x136/images/anime/1715/103419.jpg?s=bb42a50d4b865f3e01bda0d866d010ab","is_added_to_list":false,"anime_media_type_string":"TV","anime_mpaa_rating_string":"PG-13","start_date_string":null,"finish_date_string":null,"anime_start_date_string":"02-10-19","anime_end_date_string":"27-12-19","days_string":null,"storage_string":"","priority_string":"Low"},{"status":2,"score":0,"tags":"","is_rewatching":0,"num_watched_episodes":24,"anime_title":"Shokugeki no Souma","anime_title_eng":"Food Wars! Shokugeki no Soma","anime_num_episodes":24,"anime_airing_status":2,"anime_id":28171,"anime_studios":null,"anime_licensors":null,"anime_season":null,"has_episode_video":true,"has_promotion_video":true,"has_video":true,"video_url":"/anime/28171/Shokugeki_no_Souma/video","genres":[{"id":47,"name":"Gourmet"},{"id":9,"name":"Ecchi"}],"demographics":[{"id":27,"name":"Shounen"}],"title_localized":null,"anime_url":"/anime/28171/Shokugeki_no_Souma","anime_image_path":"https://cdn.myanimelist.net/r/96x136/images/anime/3/72943.jpg?s=622a5923ec7c0915e78ab7b90144f9c6","is_added_to_list":false,"anime_media_type_string":"TV","anime_mpaa_rating_string":"PG-13","start_date_string":null,"finish_date_string":null,"anime_start_date_string":"04-04-15","anime_end_date_string":"26-09-15","days_string":null,"storage_string":"","priority_string":"Low"},{"status":2,"score":0,"tags":"","is_rewatching":0,"num_watched_episodes":12,"anime_title":"Uzaki-chan wa Asobitai!","anime_title_eng":"Uzaki-chan Wants to Hang Out!","anime_num_episodes":12,"anime_airing_status":2,"anime_id":41226,"anime_studios":null,"anime_licensors":null,"anime_season":null,"has_episode_video":false,"has_promotion_video":true,"has_video":true,"video_url":"/anime/41226/Uzaki-chan_wa_Asobitai/video","genres":[{"id":4,"name":"Comedy"},{"id":22,"name":"Romance"},{"id":36,"name":"Slice of Life"},{"id":9,"name":"Ecchi"}],"demographics":[],"title_localized":null,"anime_url":"/anime/41226/Uzaki-chan_wa_Asobitai","anime_image_path":"https://cdn.myanimelist.net/r/96x136/images/anime/1540/108292.jpg?s=4d5fc588cb16d6373982b866fc086570","is_added_to_list":false,"anime_media_type_string":"TV","anime_mpaa_rating_string":"PG-13","start_date_string":null,"finish_date_string":null,"anime_start_date_string":"10-07-20","anime_end_date_string":"25-09-20","days_string":null,"storage_string":"","priority_string":"Low"},{"status":2,"score":0,"tags":"","is_rewatching":0,"num_watched_episodes":11,"anime_title":"Zombie-Loan","anime_title_eng":"Zombie-Loan","anime_num_episodes":11,"anime_airing_status":2,"anime_id":2404,"anime_studios":null,"anime_licensors":null,"anime_season":null,"has_episode_video":false,"has_promotion_video":false,"has_video":false,"video_url":"/anime/2404/Zombie-Loan/video","genres":[{"id":1,"name":"Action"},{"id":14,"name":"Horror"},{"id":37,"name":"Supernatural"}],"demographics":[{"id":27,"name":"Shounen"}],"title_localized":null,"anime_url":"/anime/2404/Zombie-Loan","anime_image_path":"https://cdn.myanimelist.net/r/96x136/images/anime/2/21539.jpg?s=456570d7a5360335b325f33da16c3e57","is_added_to_list":false,"anime_media_type_string":"TV","anime_mpaa_rating_string":"R","start_date_string":null,"finish_date_string":null,"anime_start_date_string":"04-07-07","anime_end_date_string":"12-09-07","days_string":null,"storage_string":"","priority_string":"Low"},{"status":3,"score":0,"tags":"","is_rewatching":0,"num_watched_episodes":0,"anime_title":"Kore wa Zombie Desu ka? of the Dead","anime_title_eng":"Is this A Zombie? of the Dead","anime_num_episodes":10,"anime_airing_status":2,"anime_id":10790,"anime_studios":null,"anime_licensors":null,"anime_season":null,"has_episode_video":false,"has_promotion_video":true,"has_video":true,"video_url":"/anime/10790/Kore_wa_Zombie_Desu_ka_of_the_Dead/video","genres":[{"id":1,"name":"Action"},{"id":4,"name":"Comedy"},{"id":37,"name":"Supernatural"},{"id":9,"name":"Ecchi"}],"demographics":[],"title_localized":null,"anime_url":"/anime/10790/Kore_wa_Zombie_Desu_ka_of_the_Dead","anime_image_path":"https://cdn.myanimelist.net/r/96x136/images/anime/4/37451.jpg?s=5dd8c914a65f90ba5ef248c3ec9b5245","is_added_to_list":false,"anime_media_type_string":"TV","anime_mpaa_rating_string":"R","start_date_string":null,"finish_date_string":null,"anime_start_date_string":"05-04-12","anime_end_date_string":"07-06-12","days_string":null,"storage_string":"","priority_string":"Low"}]